mathics3_module_base-9.0.0.dist-info/licenses/COPYING.txt
mathics3_module_base-9.0.0.dist-info/licenses/LICENSE
pymathics/__init__.py
pymathics/version.py
mathics3_module_base-9.0.0.dist-info/METADATA
mathics3_module_base-9.0.0.dist-info/WHEEL
mathics3_module_base-9.0.0.dist-info/top_level.txt
mathics3_module_base-9.0.0.dist-info/RECORD
